pytos/__init__.py
pytos/common/__init__.py
pytos/common/base_types.py
pytos/common/exceptions.py
pytos/common/helpers.py
pytos/common/rest_requests.py
pytos/common/definitions/Url_Params_Builder.py
pytos/common/definitions/__init__.py
pytos/common/definitions/xml_tags.py
pytos/common/functions/__init__.py
pytos/common/functions/config.py
pytos/common/functions/file_monitor.py
pytos/common/functions/network.py
pytos/common/functions/string.py
pytos/common/functions/tos.py
pytos/common/functions/utils.py
pytos/common/functions/xml.py
pytos/common/logging/__init__.py
pytos/common/logging/definitions.py
pytos/common/logging/logger.py
pytos/secureapp/__init__.py
pytos/secureapp/definitions.py
pytos/secureapp/helpers.py
pytos/secureapp/xml_objects/__init__.py
pytos/secureapp/xml_objects/base_types.py
pytos/secureapp/xml_objects/rest.py
pytos/securechange/__init__.py
pytos/securechange/definitions.py
pytos/securechange/helpers.py
pytos/securechange/templates/risk_analysis_template.html
pytos/securechange/xml_objects/__init__.py
pytos/securechange/xml_objects/base_types.py
pytos/securechange/xml_objects/rest.py
pytos/securechange/xml_objects/securechange_api.py
pytos/securechange/xml_objects/restapi/__init__.py
pytos/securechange/xml_objects/restapi/step/__init__.py
pytos/securechange/xml_objects/restapi/step/initialize.py
pytos/securechange/xml_objects/restapi/step/step.py
pytos/securechange/xml_objects/restapi/step/access_request/__init__.py
pytos/securechange/xml_objects/restapi/step/access_request/accessrequest.py
pytos/securechange/xml_objects/restapi/step/access_request/analysisresult.py
pytos/securechange/xml_objects/restapi/step/access_request/designer.py
pytos/securechange/xml_objects/restapi/step/access_request/risk.py
pytos/securechange/xml_objects/restapi/step/access_request/verifier.py
pytos/securechange/xml_objects/restapi/step/rule_decommission/__init__.py
pytos/securechange/xml_objects/restapi/step/rule_decommission/rule_decommission.py
pytos-1.2.8.dist-info/LICENSE.md
pytos-1.2.8.dist-info/METADATA
pytos-1.2.8.dist-info/WHEEL
pytos-1.2.8.dist-info/pbr.json
pytos-1.2.8.dist-info/top_level.txt
pytos-1.2.8.dist-info/RECORD
