Metadata-Version: 2.1
Name: pytos
Version: 1.2.8
Summary: The Tufin TOS SDK for Python
Home-page: http://pypi.python.org/pypi/pytos
Author: Tufin Solution Engineering
Author-email: support@tufin.com
License: Apache License 2.0
Platform: UNKNOWN
Classifier: Development Status :: 5 - Production/Stable
Classifier: Intended Audience :: Developers
Classifier: Topic :: Software Development :: Libraries :: Python Modules
Classifier: Natural Language :: English
Classifier: License :: OSI Approved :: Apache Software License
Classifier: Programming Language :: Python :: 3.4
Classifier: Programming Language :: Python :: 3.5
Classifier: Programming Language :: Python :: 3.6
Requires-Dist: netaddr (>=0.7.14)
Requires-Dist: paramiko (>=1.15.2)
Requires-Dist: requests (>=2.6.0)
Requires-Dist: requests-toolbelt (==0.7.1)
Requires-Dist: netifaces (==0.10.9)
Requires-Dist: dnspython3 (==1.15.0)
Requires-Dist: Mako
